datamine/__init__.py
datamine/core.py
thedatamine/__init__.py
thedatamine/core.py
thedatamine-0.1.3.dist-info/LICENSE
thedatamine-0.1.3.dist-info/METADATA
thedatamine-0.1.3.dist-info/WHEEL
thedatamine-0.1.3.dist-info/top_level.txt
thedatamine-0.1.3.dist-info/RECORD
