Metadata-Version: 2.1
Name: thedatamine
Version: 0.1.3
Summary: Course package for Purdue University's integrative data science initiative, The Data Mine.
Home-page: https://github.com/TheDataMine/thedatamine_py
Author: Kevin Amstutz
Author-email: kevin@amstutz.io
License: UNKNOWN
Platform: UNKNOWN
Classifier: Programming Language :: Python :: 3
Classifier: License :: OSI Approved :: MIT License
Classifier: Operating System :: OS Independent
Requires-Python: >=3.8
